aioinject/__init__.py
aioinject/_types.py
aioinject/container.py
aioinject/context.py
aioinject/decorators.py
aioinject/dependencies.py
aioinject/errors.py
aioinject/py.typed
aioinject/scope.py
aioinject/_compilation/__init__.py
aioinject/_compilation/compile.py
aioinject/_compilation/naming.py
aioinject/_compilation/resolve.py
aioinject/_compilation/util.py
aioinject/_internal/__init__.py
aioinject/_internal/type_sources.py
aioinject/ext/__init__.py
aioinject/ext/aiogram.py
aioinject/ext/django.py
aioinject/ext/fastapi.py
aioinject/ext/grpcio.py
aioinject/ext/litestar.py
aioinject/ext/strawberry.py
aioinject/extensions/__init__.py
aioinject/extensions/_abc.py
aioinject/extensions/providers.py
aioinject/providers/__init__.py
aioinject/providers/abc.py
aioinject/providers/context.py
aioinject/providers/object.py
aioinject/providers/scoped.py
aioinject/testing/__init__.py
aioinject/testing/testcontainer.py
aioinject/validation/__init__.py
aioinject/validation/abc.py
aioinject/validation/errors.py
aioinject/validation/rules.py
aioinject/validation/validate.py
aioinject-1.10.1.dist-info/METADATA
aioinject-1.10.1.dist-info/WHEEL
aioinject-1.10.1.dist-info/licenses/LICENSE
aioinject-1.10.1.dist-info/RECORD
