Metadata-Version: 2.4
Name: aioinject
Version: 1.10.1
Summary: Async dependency injection library
Project-URL: Documentation, https://notypecheck.github.io/aioinject/
Project-URL: Repository, https://github.com/notypecheck/aioinject
Author-email: Doctor <notypecheck@gmail.com>, dexofan <fadeddexofan@gmail.com>
License: MIT
License-File: LICENSE
Classifier: License :: OSI Approved :: MIT License
Requires-Python: >=3.10
Requires-Dist: typing-extensions>=4.10.0
